dlx.cpython-314-darwin.so
dlxsolver.py
dlx_cython-0.1.6.dist-info/licenses/LICENSE
dlx_cython-0.1.6.dist-info/METADATA
dlx_cython-0.1.6.dist-info/WHEEL
dlx_cython-0.1.6.dist-info/top_level.txt
dlx_cython-0.1.6.dist-info/RECORD
